mmforms/__init__.py
mmforms/_base_elements.py
mmforms/bootstrap_elements.py
mmforms/factories.py
mmforms/standard_elements.py
mmforms-0.0.6.dist-info/LICENSE
mmforms-0.0.6.dist-info/METADATA
mmforms-0.0.6.dist-info/WHEEL
mmforms-0.0.6.dist-info/top_level.txt
mmforms-0.0.6.dist-info/RECORD
