Metadata-Version: 2.1
Name: mmforms
Version: 0.0.6
Summary: Markup generated by Methods, Forms. HTML Forms generated by method chaining.
Home-page: https://github.com/CheeseCake87/mmforms
Author: David Carmichael
License: GNU General Public License v2 or later (GPLv2+)
Keywords: mmforms flask forms markup
Platform: any
Classifier: Development Status :: 5 - Production/Stable
Classifier: Framework :: Flask
Classifier: Intended Audience :: Developers
Classifier: Intended Audience :: Science/Research
Classifier: Intended Audience :: System Administrators
Classifier: License :: OSI Approved :: GNU General Public License v2 or later (GPLv2+)
Classifier: Natural Language :: English
Classifier: Programming Language :: Python :: 3.8
Classifier: Topic :: Internet :: WWW/HTTP
Requires-Python: >=3.8
License-File: LICENSE
Requires-Dist: MarkupSafe
